mux/mux21/mux21.v
module mux21(a,b,s,y);
	input a,b,s;
	output y;

	assign y = s ? a : b;
endmodule

mux/mux21/waveform.vcd
$version Generated by VerilatedVcd $end
$date Tue Nov 22 05:03:00 2022 $end
$timescale 1s $end

 $scope module TOP $end
  $var wire  1 # a $end
  $var wire  1 $ b $end
  $var wire  1 % s $end
  $var wire  1 & y $end
  $scope module mux21 $end
   $var wire  1 # a $end
   $var wire  1 $ b $end
   $var wire  1 % s $end
   $var wire  1 & y $end
  $upscope $end
 $upscope $end
$enddefinitions $end


#1
0#
0$
0%
0&
#2
1$
1&
#3
1#
0$
0&
#4
1$
1&
#5
0#
0$
1%
0&
#6
1$
#7
1#
0$
1&
#8
1$
