decode24/vsrc/top.v
module top(x, en, y);
    input [1:0] x;
    input en;
    output reg [3:0] y;

  always @(*) begin
    if(en) begin
        case (x)
            2'd0 : y = 4'b0001;
            2'd1 : y = 4'b0010;
            2'd2 : y = 4'b0100;
            2'd3 : y = 4'b1000;
        endcase
    end
    else begin
        y = 4'b0000;
    end
  end

endmodule

decode24/waveform.vcd
$version Generated by VerilatedVcd $end
$date Thu Nov 24 15:49:21 2022 $end
$timescale 1s $end

 $scope module TOP $end
  $var wire  1 $ en $end
  $var wire  2 # x [1:0] $end
  $var wire  4 % y [3:0] $end
  $scope module top $end
   $var wire  1 $ en $end
   $var wire  2 # x [1:0] $end
   $var wire  4 % y [3:0] $end
  $upscope $end
 $upscope $end
$enddefinitions $end


#0
b00 #
0$
b0000 %
#1
b01 #
#2
b10 #
#3
b11 #
#4
b00 #
1$
b0001 %
#5
b01 #
b0010 %
#6
b10 #
b0100 %
#7
b11 #
b1000 %
